knnmv/__init__.py
knnmv/impute.py
knnmv/metrics.py
knnmv-0.0.3.dist-info/LICENSE
knnmv-0.0.3.dist-info/METADATA
knnmv-0.0.3.dist-info/WHEEL
knnmv-0.0.3.dist-info/top_level.txt
knnmv-0.0.3.dist-info/RECORD
