Metadata-Version: 2.1
Name: knnmv
Version: 0.0.3
Summary: Sparsity aware KNN imputation.
Home-page: https://github.com/massibelloni/knnmv
Author: Massimo Belloni
Author-email: massibelloni@gmail.com
License: UNKNOWN
Platform: UNKNOWN
Classifier: Programming Language :: Python :: 3
Classifier: License :: OSI Approved :: MIT License
Classifier: Operating System :: OS Independent
Requires-Dist: numpy
Requires-Dist: scikit-learn
